ShenruLijieAndroidJuanIii/README.md
ShenruLijieAndroidJuanIii/__init__.py
ShenruLijieAndroidJuanIii/__main__.py
ShenruLijieAndroidJuanIii/file.epub
ShenruLijieAndroidJuanIii/index.html
ShenruLijieAndroidJuanIii/css/__init__.py
ShenruLijieAndroidJuanIii/css/annotations.css
ShenruLijieAndroidJuanIii/css/main.css
ShenruLijieAndroidJuanIii/css/normalize.css
ShenruLijieAndroidJuanIii/css/popup.css
ShenruLijieAndroidJuanIii/font/__init__.py
ShenruLijieAndroidJuanIii/font/fontello.eot
ShenruLijieAndroidJuanIii/font/fontello.svg
ShenruLijieAndroidJuanIii/font/fontello.ttf
ShenruLijieAndroidJuanIii/font/fontello.woff
ShenruLijieAndroidJuanIii/img/__init__.py
ShenruLijieAndroidJuanIii/img/annotator-glyph-sprite.png
ShenruLijieAndroidJuanIii/img/annotator-icon-sprite.png
ShenruLijieAndroidJuanIii/img/apple-touch-icon.png
ShenruLijieAndroidJuanIii/img/cancelfullscreen.png
ShenruLijieAndroidJuanIii/img/close.png
ShenruLijieAndroidJuanIii/img/fullscreen.png
ShenruLijieAndroidJuanIii/img/loader.gif
ShenruLijieAndroidJuanIii/img/menu-icon.png
ShenruLijieAndroidJuanIii/img/save.png
ShenruLijieAndroidJuanIii/img/saved.png
ShenruLijieAndroidJuanIii/img/settings-s.png
ShenruLijieAndroidJuanIii/img/settings.png
ShenruLijieAndroidJuanIii/img/star.png
ShenruLijieAndroidJuanIii/js/__init__.py
ShenruLijieAndroidJuanIii/js/epub.js
ShenruLijieAndroidJuanIii/js/epub.min.js
ShenruLijieAndroidJuanIii/js/epub.min.map
ShenruLijieAndroidJuanIii/js/hooks.min.js
ShenruLijieAndroidJuanIii/js/hooks.min.map
ShenruLijieAndroidJuanIii/js/reader.js
ShenruLijieAndroidJuanIii/js/reader.js.map
ShenruLijieAndroidJuanIii/js/reader.min.js
ShenruLijieAndroidJuanIii/js/reader.min.map
ShenruLijieAndroidJuanIii/js/hooks/__init__.py
ShenruLijieAndroidJuanIii/js/hooks/extensions/__init__.py
ShenruLijieAndroidJuanIii/js/hooks/extensions/highlight.js
ShenruLijieAndroidJuanIii/js/libs/__init__.py
ShenruLijieAndroidJuanIii/js/libs/jquery.min.js
ShenruLijieAndroidJuanIii/js/libs/localforage.min.js
shenru_lijie_android_juan_iii-2024.3.2.0.dist-info/METADATA
shenru_lijie_android_juan_iii-2024.3.2.0.dist-info/WHEEL
shenru_lijie_android_juan_iii-2024.3.2.0.dist-info/entry_points.txt
shenru_lijie_android_juan_iii-2024.3.2.0.dist-info/top_level.txt
shenru_lijie_android_juan_iii-2024.3.2.0.dist-info/RECORD
